LICENSE
MANIFEST.in
README.md
requirements.txt
setup.py
R305.egg-info/PKG-INFO
R305.egg-info/SOURCES.txt
R305.egg-info/dependency_links.txt
R305.egg-info/requires.txt
R305.egg-info/top_level.txt
r305/__init__.py
r305/device.py
r305/r305.py