Metadata-Version: 1.0
Name: R305
Version: 2.0.0
Summary: python api for R305 finger print module
Home-page: UNKNOWN
Author: girish joshi
Author-email: girish946@gmail.com
License: GPL v3
Keywords: python api for R305 finger print module
Platform: UNKNOWN
